mfbm/__init__.py
mfbm/fbm.py
mfbm/mfbm.py
mfbm/utils.py
mfbm-0.1.3.dist-info/METADATA
mfbm-0.1.3.dist-info/WHEEL
mfbm-0.1.3.dist-info/top_level.txt
mfbm-0.1.3.dist-info/RECORD
