Metadata-Version: 2.4
Name: mfbm
Version: 0.1.3
Summary: Multivariate fractional Brownian motion
Author-email: Leonardo Toffalini <leonardotoffalini@gmail.com>
License: MIT
Project-URL: Homepage, https://github.com/leonardo-toffalini/mfbm
Classifier: Programming Language :: Python :: 3
Classifier: License :: OSI Approved :: MIT License
Classifier: Operating System :: OS Independent
Requires-Python: >=3.7
Requires-Dist: numpy
